{
  "id": "083e8e36-a115-4b99-8894-9be096586da1",
  "prevId": "00000000-0000-0000-0000-000000000000",
  "version": "7",
  "dialect": "postgresql",
  "tables": {
    "public.alert_rules": {
      "name": "alert_rules",
      "schema": "",
      "columns": {
        "id": {
          "name": "id",
          "type": "uuid",
          "primaryKey": true,
          "notNull": true,
          "default": "gen_random_uuid()"
        },
        "product_id": {
          "name": "product_id",
          "type": "text",
          "primaryKey": false,
          "notNull": true
        },
        "name": {
          "name": "name",
          "type": "text",
          "primaryKey": false,
          "notNull": true
        },
        "description": {
          "name": "description",
          "type": "text",
          "primaryKey": false,
          "notNull": false
        },
        "condition": {
          "name": "condition",
          "type": "jsonb",
          "primaryKey": false,
          "notNull": true
        },
        "channels": {
          "name": "channels",
          "type": "jsonb",
          "primaryKey": false,
          "notNull": true,
          "default": "'[]'::jsonb"
        },
        "enabled": {
          "name": "enabled",
          "type": "boolean",
          "primaryKey": false,
          "notNull": true,
          "default": true
        },
        "last_triggered_at": {
          "name": "last_triggered_at",
          "type": "timestamp with time zone",
          "primaryKey": false,
          "notNull": false
        },
        "created_at": {
          "name": "created_at",
          "type": "timestamp with time zone",
          "primaryKey": false,
          "notNull": true,
          "default": "now()"
        },
        "updated_at": {
          "name": "updated_at",
          "type": "timestamp with time zone",
          "primaryKey": false,
          "notNull": true,
          "default": "now()"
        }
      },
      "indexes": {
        "alert_rules_product_enabled_idx": {
          "name": "alert_rules_product_enabled_idx",
          "columns": [
            {
              "expression": "product_id",
              "isExpression": false,
              "asc": true,
              "nulls": "last"
            },
            {
              "expression": "enabled",
              "isExpression": false,
              "asc": true,
              "nulls": "last"
            }
          ],
          "isUnique": false,
          "concurrently": false,
          "method": "btree",
          "with": {}
        }
      },
      "foreignKeys": {
        "alert_rules_product_id_products_id_fk": {
          "name": "alert_rules_product_id_products_id_fk",
          "tableFrom": "alert_rules",
          "tableTo": "products",
          "columnsFrom": [
            "product_id"
          ],
          "columnsTo": [
            "id"
          ],
          "onDelete": "cascade",
          "onUpdate": "no action"
        }
      },
      "compositePrimaryKeys": {},
      "uniqueConstraints": {}
    },
    "public.alerts": {
      "name": "alerts",
      "schema": "",
      "columns": {
        "id": {
          "name": "id",
          "type": "uuid",
          "primaryKey": true,
          "notNull": true,
          "default": "gen_random_uuid()"
        },
        "rule_id": {
          "name": "rule_id",
          "type": "uuid",
          "primaryKey": false,
          "notNull": true
        },
        "product_id": {
          "name": "product_id",
          "type": "text",
          "primaryKey": false,
          "notNull": true
        },
        "title": {
          "name": "title",
          "type": "text",
          "primaryKey": false,
          "notNull": true
        },
        "severity": {
          "name": "severity",
          "type": "text",
          "primaryKey": false,
          "notNull": true,
          "default": "'warning'"
        },
        "context": {
          "name": "context",
          "type": "jsonb",
          "primaryKey": false,
          "notNull": true,
          "default": "'{}'::jsonb"
        },
        "status": {
          "name": "status",
          "type": "alert_status",
          "typeSchema": "public",
          "primaryKey": false,
          "notNull": true,
          "default": "'firing'"
        },
        "triggered_at": {
          "name": "triggered_at",
          "type": "timestamp with time zone",
          "primaryKey": false,
          "notNull": true,
          "default": "now()"
        },
        "resolved_at": {
          "name": "resolved_at",
          "type": "timestamp with time zone",
          "primaryKey": false,
          "notNull": false
        }
      },
      "indexes": {
        "alerts_product_status_idx": {
          "name": "alerts_product_status_idx",
          "columns": [
            {
              "expression": "product_id",
              "isExpression": false,
              "asc": true,
              "nulls": "last"
            },
            {
              "expression": "status",
              "isExpression": false,
              "asc": true,
              "nulls": "last"
            },
            {
              "expression": "triggered_at",
              "isExpression": false,
              "asc": true,
              "nulls": "last"
            }
          ],
          "isUnique": false,
          "concurrently": false,
          "method": "btree",
          "with": {}
        }
      },
      "foreignKeys": {
        "alerts_rule_id_alert_rules_id_fk": {
          "name": "alerts_rule_id_alert_rules_id_fk",
          "tableFrom": "alerts",
          "tableTo": "alert_rules",
          "columnsFrom": [
            "rule_id"
          ],
          "columnsTo": [
            "id"
          ],
          "onDelete": "cascade",
          "onUpdate": "no action"
        }
      },
      "compositePrimaryKeys": {},
      "uniqueConstraints": {}
    },
    "public.clusters": {
      "name": "clusters",
      "schema": "",
      "columns": {
        "id": {
          "name": "id",
          "type": "uuid",
          "primaryKey": true,
          "notNull": true,
          "default": "gen_random_uuid()"
        },
        "product_id": {
          "name": "product_id",
          "type": "text",
          "primaryKey": false,
          "notNull": true
        },
        "name": {
          "name": "name",
          "type": "text",
          "primaryKey": false,
          "notNull": true
        },
        "description": {
          "name": "description",
          "type": "text",
          "primaryKey": false,
          "notNull": false
        },
        "category": {
          "name": "category",
          "type": "text",
          "primaryKey": false,
          "notNull": false
        },
        "representative_event_ids": {
          "name": "representative_event_ids",
          "type": "uuid[]",
          "primaryKey": false,
          "notNull": true,
          "default": "'{}'"
        },
        "event_count_total": {
          "name": "event_count_total",
          "type": "integer",
          "primaryKey": false,
          "notNull": true,
          "default": 0
        },
        "event_count_24h": {
          "name": "event_count_24h",
          "type": "integer",
          "primaryKey": false,
          "notNull": true,
          "default": 0
        },
        "event_count_7d": {
          "name": "event_count_7d",
          "type": "integer",
          "primaryKey": false,
          "notNull": true,
          "default": 0
        },
        "trend": {
          "name": "trend",
          "type": "jsonb",
          "primaryKey": false,
          "notNull": true,
          "default": "'[]'::jsonb"
        },
        "status": {
          "name": "status",
          "type": "cluster_status",
          "typeSchema": "public",
          "primaryKey": false,
          "notNull": true,
          "default": "'active'"
        },
        "root_cause_analysis": {
          "name": "root_cause_analysis",
          "type": "text",
          "primaryKey": false,
          "notNull": false
        },
        "suggested_fix": {
          "name": "suggested_fix",
          "type": "text",
          "primaryKey": false,
          "notNull": false
        },
        "created_at": {
          "name": "created_at",
          "type": "timestamp with time zone",
          "primaryKey": false,
          "notNull": true,
          "default": "now()"
        },
        "updated_at": {
          "name": "updated_at",
          "type": "timestamp with time zone",
          "primaryKey": false,
          "notNull": true,
          "default": "now()"
        }
      },
      "indexes": {
        "clusters_product_status_idx": {
          "name": "clusters_product_status_idx",
          "columns": [
            {
              "expression": "product_id",
              "isExpression": false,
              "asc": true,
              "nulls": "last"
            },
            {
              "expression": "status",
              "isExpression": false,
              "asc": true,
              "nulls": "last"
            }
          ],
          "isUnique": false,
          "concurrently": false,
          "method": "btree",
          "with": {}
        },
        "clusters_product_category_idx": {
          "name": "clusters_product_category_idx",
          "columns": [
            {
              "expression": "product_id",
              "isExpression": false,
              "asc": true,
              "nulls": "last"
            },
            {
              "expression": "category",
              "isExpression": false,
              "asc": true,
              "nulls": "last"
            }
          ],
          "isUnique": false,
          "concurrently": false,
          "method": "btree",
          "with": {}
        }
      },
      "foreignKeys": {
        "clusters_product_id_products_id_fk": {
          "name": "clusters_product_id_products_id_fk",
          "tableFrom": "clusters",
          "tableTo": "products",
          "columnsFrom": [
            "product_id"
          ],
          "columnsTo": [
            "id"
          ],
          "onDelete": "cascade",
          "onUpdate": "no action"
        }
      },
      "compositePrimaryKeys": {},
      "uniqueConstraints": {}
    },
    "public.events": {
      "name": "events",
      "schema": "",
      "columns": {
        "id": {
          "name": "id",
          "type": "uuid",
          "primaryKey": true,
          "notNull": true,
          "default": "gen_random_uuid()"
        },
        "product_id": {
          "name": "product_id",
          "type": "text",
          "primaryKey": false,
          "notNull": true
        },
        "org_id": {
          "name": "org_id",
          "type": "text",
          "primaryKey": false,
          "notNull": true
        },
        "conversation_id": {
          "name": "conversation_id",
          "type": "text",
          "primaryKey": false,
          "notNull": false
        },
        "user_id_hash": {
          "name": "user_id_hash",
          "type": "text",
          "primaryKey": false,
          "notNull": false
        },
        "parent_event_id": {
          "name": "parent_event_id",
          "type": "uuid",
          "primaryKey": false,
          "notNull": false
        },
        "input_message": {
          "name": "input_message",
          "type": "text",
          "primaryKey": false,
          "notNull": false
        },
        "output_message": {
          "name": "output_message",
          "type": "text",
          "primaryKey": false,
          "notNull": false
        },
        "model": {
          "name": "model",
          "type": "text",
          "primaryKey": false,
          "notNull": false
        },
        "prompt_version_id": {
          "name": "prompt_version_id",
          "type": "uuid",
          "primaryKey": false,
          "notNull": false
        },
        "prompt_version_label": {
          "name": "prompt_version_label",
          "type": "text",
          "primaryKey": false,
          "notNull": false
        },
        "tokens_input": {
          "name": "tokens_input",
          "type": "integer",
          "primaryKey": false,
          "notNull": false,
          "default": 0
        },
        "tokens_output": {
          "name": "tokens_output",
          "type": "integer",
          "primaryKey": false,
          "notNull": false,
          "default": 0
        },
        "tokens_cache_hit": {
          "name": "tokens_cache_hit",
          "type": "integer",
          "primaryKey": false,
          "notNull": false,
          "default": 0
        },
        "cost_usd": {
          "name": "cost_usd",
          "type": "double precision",
          "primaryKey": false,
          "notNull": false,
          "default": 0
        },
        "latency_ms": {
          "name": "latency_ms",
          "type": "integer",
          "primaryKey": false,
          "notNull": false,
          "default": 0
        },
        "tools_called": {
          "name": "tools_called",
          "type": "jsonb",
          "primaryKey": false,
          "notNull": true,
          "default": "'[]'::jsonb"
        },
        "scores": {
          "name": "scores",
          "type": "jsonb",
          "primaryKey": false,
          "notNull": false
        },
        "judge_reasoning": {
          "name": "judge_reasoning",
          "type": "text",
          "primaryKey": false,
          "notNull": false
        },
        "cluster_id": {
          "name": "cluster_id",
          "type": "uuid",
          "primaryKey": false,
          "notNull": false
        },
        "status": {
          "name": "status",
          "type": "text",
          "primaryKey": false,
          "notNull": true,
          "default": "'success'"
        },
        "error_message": {
          "name": "error_message",
          "type": "text",
          "primaryKey": false,
          "notNull": false
        },
        "language": {
          "name": "language",
          "type": "text",
          "primaryKey": false,
          "notNull": false
        },
        "metadata": {
          "name": "metadata",
          "type": "jsonb",
          "primaryKey": false,
          "notNull": true,
          "default": "'{}'::jsonb"
        },
        "created_at": {
          "name": "created_at",
          "type": "timestamp with time zone",
          "primaryKey": false,
          "notNull": true,
          "default": "now()"
        }
      },
      "indexes": {
        "events_product_created_idx": {
          "name": "events_product_created_idx",
          "columns": [
            {
              "expression": "product_id",
              "isExpression": false,
              "asc": true,
              "nulls": "last"
            },
            {
              "expression": "created_at",
              "isExpression": false,
              "asc": true,
              "nulls": "last"
            }
          ],
          "isUnique": false,
          "concurrently": false,
          "method": "btree",
          "with": {}
        },
        "events_conversation_idx": {
          "name": "events_conversation_idx",
          "columns": [
            {
              "expression": "conversation_id",
              "isExpression": false,
              "asc": true,
              "nulls": "last"
            }
          ],
          "isUnique": false,
          "concurrently": false,
          "method": "btree",
          "with": {}
        },
        "events_cluster_idx": {
          "name": "events_cluster_idx",
          "columns": [
            {
              "expression": "cluster_id",
              "isExpression": false,
              "asc": true,
              "nulls": "last"
            }
          ],
          "isUnique": false,
          "concurrently": false,
          "method": "btree",
          "with": {}
        },
        "events_status_idx": {
          "name": "events_status_idx",
          "columns": [
            {
              "expression": "product_id",
              "isExpression": false,
              "asc": true,
              "nulls": "last"
            },
            {
              "expression": "status",
              "isExpression": false,
              "asc": true,
              "nulls": "last"
            },
            {
              "expression": "created_at",
              "isExpression": false,
              "asc": true,
              "nulls": "last"
            }
          ],
          "isUnique": false,
          "concurrently": false,
          "method": "btree",
          "with": {}
        }
      },
      "foreignKeys": {
        "events_product_id_products_id_fk": {
          "name": "events_product_id_products_id_fk",
          "tableFrom": "events",
          "tableTo": "products",
          "columnsFrom": [
            "product_id"
          ],
          "columnsTo": [
            "id"
          ],
          "onDelete": "no action",
          "onUpdate": "no action"
        },
        "events_prompt_version_id_prompt_versions_id_fk": {
          "name": "events_prompt_version_id_prompt_versions_id_fk",
          "tableFrom": "events",
          "tableTo": "prompt_versions",
          "columnsFrom": [
            "prompt_version_id"
          ],
          "columnsTo": [
            "id"
          ],
          "onDelete": "no action",
          "onUpdate": "no action"
        }
      },
      "compositePrimaryKeys": {},
      "uniqueConstraints": {}
    },
    "public.feedback": {
      "name": "feedback",
      "schema": "",
      "columns": {
        "id": {
          "name": "id",
          "type": "uuid",
          "primaryKey": true,
          "notNull": true,
          "default": "gen_random_uuid()"
        },
        "event_id": {
          "name": "event_id",
          "type": "uuid",
          "primaryKey": false,
          "notNull": true
        },
        "product_id": {
          "name": "product_id",
          "type": "text",
          "primaryKey": false,
          "notNull": true
        },
        "rating": {
          "name": "rating",
          "type": "rating",
          "typeSchema": "public",
          "primaryKey": false,
          "notNull": true
        },
        "reasons": {
          "name": "reasons",
          "type": "text[]",
          "primaryKey": false,
          "notNull": true,
          "default": "'{}'"
        },
        "comment": {
          "name": "comment",
          "type": "text",
          "primaryKey": false,
          "notNull": false
        },
        "user_id_hash": {
          "name": "user_id_hash",
          "type": "text",
          "primaryKey": false,
          "notNull": false
        },
        "created_at": {
          "name": "created_at",
          "type": "timestamp with time zone",
          "primaryKey": false,
          "notNull": true,
          "default": "now()"
        }
      },
      "indexes": {
        "feedback_event_idx": {
          "name": "feedback_event_idx",
          "columns": [
            {
              "expression": "event_id",
              "isExpression": false,
              "asc": true,
              "nulls": "last"
            }
          ],
          "isUnique": false,
          "concurrently": false,
          "method": "btree",
          "with": {}
        },
        "feedback_product_rating_idx": {
          "name": "feedback_product_rating_idx",
          "columns": [
            {
              "expression": "product_id",
              "isExpression": false,
              "asc": true,
              "nulls": "last"
            },
            {
              "expression": "rating",
              "isExpression": false,
              "asc": true,
              "nulls": "last"
            },
            {
              "expression": "created_at",
              "isExpression": false,
              "asc": true,
              "nulls": "last"
            }
          ],
          "isUnique": false,
          "concurrently": false,
          "method": "btree",
          "with": {}
        }
      },
      "foreignKeys": {
        "feedback_event_id_events_id_fk": {
          "name": "feedback_event_id_events_id_fk",
          "tableFrom": "feedback",
          "tableTo": "events",
          "columnsFrom": [
            "event_id"
          ],
          "columnsTo": [
            "id"
          ],
          "onDelete": "cascade",
          "onUpdate": "no action"
        }
      },
      "compositePrimaryKeys": {},
      "uniqueConstraints": {}
    },
    "public.golden_cases": {
      "name": "golden_cases",
      "schema": "",
      "columns": {
        "id": {
          "name": "id",
          "type": "uuid",
          "primaryKey": true,
          "notNull": true,
          "default": "gen_random_uuid()"
        },
        "product_id": {
          "name": "product_id",
          "type": "text",
          "primaryKey": false,
          "notNull": true
        },
        "input": {
          "name": "input",
          "type": "text",
          "primaryKey": false,
          "notNull": true
        },
        "expected_criteria": {
          "name": "expected_criteria",
          "type": "text",
          "primaryKey": false,
          "notNull": true
        },
        "category": {
          "name": "category",
          "type": "text",
          "primaryKey": false,
          "notNull": false
        },
        "difficulty": {
          "name": "difficulty",
          "type": "text",
          "primaryKey": false,
          "notNull": true,
          "default": "'medium'"
        },
        "weight": {
          "name": "weight",
          "type": "integer",
          "primaryKey": false,
          "notNull": true,
          "default": 1
        },
        "enabled": {
          "name": "enabled",
          "type": "boolean",
          "primaryKey": false,
          "notNull": true,
          "default": true
        },
        "metadata": {
          "name": "metadata",
          "type": "jsonb",
          "primaryKey": false,
          "notNull": true,
          "default": "'{}'::jsonb"
        },
        "created_at": {
          "name": "created_at",
          "type": "timestamp with time zone",
          "primaryKey": false,
          "notNull": true,
          "default": "now()"
        }
      },
      "indexes": {
        "golden_cases_product_idx": {
          "name": "golden_cases_product_idx",
          "columns": [
            {
              "expression": "product_id",
              "isExpression": false,
              "asc": true,
              "nulls": "last"
            },
            {
              "expression": "enabled",
              "isExpression": false,
              "asc": true,
              "nulls": "last"
            }
          ],
          "isUnique": false,
          "concurrently": false,
          "method": "btree",
          "with": {}
        }
      },
      "foreignKeys": {
        "golden_cases_product_id_products_id_fk": {
          "name": "golden_cases_product_id_products_id_fk",
          "tableFrom": "golden_cases",
          "tableTo": "products",
          "columnsFrom": [
            "product_id"
          ],
          "columnsTo": [
            "id"
          ],
          "onDelete": "cascade",
          "onUpdate": "no action"
        }
      },
      "compositePrimaryKeys": {},
      "uniqueConstraints": {}
    },
    "public.orgs": {
      "name": "orgs",
      "schema": "",
      "columns": {
        "id": {
          "name": "id",
          "type": "text",
          "primaryKey": true,
          "notNull": true
        },
        "name": {
          "name": "name",
          "type": "text",
          "primaryKey": false,
          "notNull": true
        },
        "created_at": {
          "name": "created_at",
          "type": "timestamp with time zone",
          "primaryKey": false,
          "notNull": true,
          "default": "now()"
        },
        "updated_at": {
          "name": "updated_at",
          "type": "timestamp with time zone",
          "primaryKey": false,
          "notNull": true,
          "default": "now()"
        }
      },
      "indexes": {},
      "foreignKeys": {},
      "compositePrimaryKeys": {},
      "uniqueConstraints": {}
    },
    "public.products": {
      "name": "products",
      "schema": "",
      "columns": {
        "id": {
          "name": "id",
          "type": "text",
          "primaryKey": true,
          "notNull": true
        },
        "org_id": {
          "name": "org_id",
          "type": "text",
          "primaryKey": false,
          "notNull": true
        },
        "name": {
          "name": "name",
          "type": "text",
          "primaryKey": false,
          "notNull": true
        },
        "description": {
          "name": "description",
          "type": "text",
          "primaryKey": false,
          "notNull": false
        },
        "owner_team": {
          "name": "owner_team",
          "type": "text",
          "primaryKey": false,
          "notNull": false
        },
        "api_key_hash": {
          "name": "api_key_hash",
          "type": "text",
          "primaryKey": false,
          "notNull": true
        },
        "enabled": {
          "name": "enabled",
          "type": "boolean",
          "primaryKey": false,
          "notNull": true,
          "default": true
        },
        "settings": {
          "name": "settings",
          "type": "jsonb",
          "primaryKey": false,
          "notNull": true,
          "default": "'{}'::jsonb"
        },
        "created_at": {
          "name": "created_at",
          "type": "timestamp with time zone",
          "primaryKey": false,
          "notNull": true,
          "default": "now()"
        },
        "updated_at": {
          "name": "updated_at",
          "type": "timestamp with time zone",
          "primaryKey": false,
          "notNull": true,
          "default": "now()"
        }
      },
      "indexes": {
        "products_org_idx": {
          "name": "products_org_idx",
          "columns": [
            {
              "expression": "org_id",
              "isExpression": false,
              "asc": true,
              "nulls": "last"
            }
          ],
          "isUnique": false,
          "concurrently": false,
          "method": "btree",
          "with": {}
        },
        "products_api_key_idx": {
          "name": "products_api_key_idx",
          "columns": [
            {
              "expression": "api_key_hash",
              "isExpression": false,
              "asc": true,
              "nulls": "last"
            }
          ],
          "isUnique": false,
          "concurrently": false,
          "method": "btree",
          "with": {}
        }
      },
      "foreignKeys": {
        "products_org_id_orgs_id_fk": {
          "name": "products_org_id_orgs_id_fk",
          "tableFrom": "products",
          "tableTo": "orgs",
          "columnsFrom": [
            "org_id"
          ],
          "columnsTo": [
            "id"
          ],
          "onDelete": "no action",
          "onUpdate": "no action"
        }
      },
      "compositePrimaryKeys": {},
      "uniqueConstraints": {}
    },
    "public.prompt_versions": {
      "name": "prompt_versions",
      "schema": "",
      "columns": {
        "id": {
          "name": "id",
          "type": "uuid",
          "primaryKey": true,
          "notNull": true,
          "default": "gen_random_uuid()"
        },
        "product_id": {
          "name": "product_id",
          "type": "text",
          "primaryKey": false,
          "notNull": true
        },
        "version": {
          "name": "version",
          "type": "text",
          "primaryKey": false,
          "notNull": true
        },
        "content": {
          "name": "content",
          "type": "text",
          "primaryKey": false,
          "notNull": true
        },
        "diff_from_parent": {
          "name": "diff_from_parent",
          "type": "text",
          "primaryKey": false,
          "notNull": false
        },
        "is_current": {
          "name": "is_current",
          "type": "boolean",
          "primaryKey": false,
          "notNull": true,
          "default": false
        },
        "metrics": {
          "name": "metrics",
          "type": "jsonb",
          "primaryKey": false,
          "notNull": true,
          "default": "'{}'::jsonb"
        },
        "deployed_at": {
          "name": "deployed_at",
          "type": "timestamp with time zone",
          "primaryKey": false,
          "notNull": false
        },
        "created_at": {
          "name": "created_at",
          "type": "timestamp with time zone",
          "primaryKey": false,
          "notNull": true,
          "default": "now()"
        }
      },
      "indexes": {
        "prompt_versions_product_idx": {
          "name": "prompt_versions_product_idx",
          "columns": [
            {
              "expression": "product_id",
              "isExpression": false,
              "asc": true,
              "nulls": "last"
            },
            {
              "expression": "version",
              "isExpression": false,
              "asc": true,
              "nulls": "last"
            }
          ],
          "isUnique": false,
          "concurrently": false,
          "method": "btree",
          "with": {}
        }
      },
      "foreignKeys": {
        "prompt_versions_product_id_products_id_fk": {
          "name": "prompt_versions_product_id_products_id_fk",
          "tableFrom": "prompt_versions",
          "tableTo": "products",
          "columnsFrom": [
            "product_id"
          ],
          "columnsTo": [
            "id"
          ],
          "onDelete": "cascade",
          "onUpdate": "no action"
        }
      },
      "compositePrimaryKeys": {},
      "uniqueConstraints": {}
    },
    "public.regression_runs": {
      "name": "regression_runs",
      "schema": "",
      "columns": {
        "id": {
          "name": "id",
          "type": "uuid",
          "primaryKey": true,
          "notNull": true,
          "default": "gen_random_uuid()"
        },
        "product_id": {
          "name": "product_id",
          "type": "text",
          "primaryKey": false,
          "notNull": true
        },
        "prompt_version_id": {
          "name": "prompt_version_id",
          "type": "uuid",
          "primaryKey": false,
          "notNull": false
        },
        "total_cases": {
          "name": "total_cases",
          "type": "integer",
          "primaryKey": false,
          "notNull": true,
          "default": 0
        },
        "passed_cases": {
          "name": "passed_cases",
          "type": "integer",
          "primaryKey": false,
          "notNull": true,
          "default": 0
        },
        "failed_cases": {
          "name": "failed_cases",
          "type": "integer",
          "primaryKey": false,
          "notNull": true,
          "default": 0
        },
        "results": {
          "name": "results",
          "type": "jsonb",
          "primaryKey": false,
          "notNull": true,
          "default": "'[]'::jsonb"
        },
        "triggered_by": {
          "name": "triggered_by",
          "type": "text",
          "primaryKey": false,
          "notNull": false
        },
        "triggered_by_user": {
          "name": "triggered_by_user",
          "type": "text",
          "primaryKey": false,
          "notNull": false
        },
        "status": {
          "name": "status",
          "type": "regression_status",
          "typeSchema": "public",
          "primaryKey": false,
          "notNull": true,
          "default": "'queued'"
        },
        "error": {
          "name": "error",
          "type": "text",
          "primaryKey": false,
          "notNull": false
        },
        "created_at": {
          "name": "created_at",
          "type": "timestamp with time zone",
          "primaryKey": false,
          "notNull": true,
          "default": "now()"
        },
        "completed_at": {
          "name": "completed_at",
          "type": "timestamp with time zone",
          "primaryKey": false,
          "notNull": false
        }
      },
      "indexes": {
        "regression_runs_product_idx": {
          "name": "regression_runs_product_idx",
          "columns": [
            {
              "expression": "product_id",
              "isExpression": false,
              "asc": true,
              "nulls": "last"
            },
            {
              "expression": "created_at",
              "isExpression": false,
              "asc": true,
              "nulls": "last"
            }
          ],
          "isUnique": false,
          "concurrently": false,
          "method": "btree",
          "with": {}
        }
      },
      "foreignKeys": {
        "regression_runs_product_id_products_id_fk": {
          "name": "regression_runs_product_id_products_id_fk",
          "tableFrom": "regression_runs",
          "tableTo": "products",
          "columnsFrom": [
            "product_id"
          ],
          "columnsTo": [
            "id"
          ],
          "onDelete": "cascade",
          "onUpdate": "no action"
        },
        "regression_runs_prompt_version_id_prompt_versions_id_fk": {
          "name": "regression_runs_prompt_version_id_prompt_versions_id_fk",
          "tableFrom": "regression_runs",
          "tableTo": "prompt_versions",
          "columnsFrom": [
            "prompt_version_id"
          ],
          "columnsTo": [
            "id"
          ],
          "onDelete": "no action",
          "onUpdate": "no action"
        }
      },
      "compositePrimaryKeys": {},
      "uniqueConstraints": {}
    }
  },
  "enums": {
    "public.alert_status": {
      "name": "alert_status",
      "schema": "public",
      "values": [
        "firing",
        "resolved"
      ]
    },
    "public.cluster_status": {
      "name": "cluster_status",
      "schema": "public",
      "values": [
        "active",
        "resolved",
        "monitoring"
      ]
    },
    "public.rating": {
      "name": "rating",
      "schema": "public",
      "values": [
        "up",
        "down",
        "neutral"
      ]
    },
    "public.regression_status": {
      "name": "regression_status",
      "schema": "public",
      "values": [
        "queued",
        "running",
        "completed",
        "failed"
      ]
    }
  },
  "schemas": {},
  "sequences": {},
  "_meta": {
    "columns": {},
    "schemas": {},
    "tables": {}
  }
}